pinit_cli-0.1.3.dist-info/licenses/LICENSE
pytool/__init__.py
pytool/cli.py
pinit_cli-0.1.3.dist-info/METADATA
pinit_cli-0.1.3.dist-info/WHEEL
pinit_cli-0.1.3.dist-info/entry_points.txt
pinit_cli-0.1.3.dist-info/top_level.txt
pinit_cli-0.1.3.dist-info/RECORD
