Metadata-Version: 2.4
Name: pinit-cli
Version: 0.1.3
Summary: A smart Python project initializer and dependency manager.
Author: Bhargav
Project-URL: Homepage, https://github.com/Bhargavxyz738/py-init
Classifier: Programming Language :: Python :: 3
Classifier: License :: OSI Approved :: MIT License
Classifier: Operating System :: OS Independent
Classifier: Environment :: Console
Classifier: Intended Audience :: Developers
Classifier: Topic :: Software Development :: Build Tools
Requires-Python: >=3.7
License-File: LICENSE
Dynamic: license-file
